djp/__init__.py
djp/hookspecs.py
djp/management/__init__.py
djp/management/commands/__init__.py
djp/management/commands/showplugins.py
djp-0.3.1.dist-info/LICENSE
djp-0.3.1.dist-info/METADATA
djp-0.3.1.dist-info/WHEEL
djp-0.3.1.dist-info/top_level.txt
djp-0.3.1.dist-info/RECORD
