Metadata-Version: 2.1
Name: djp
Version: 0.3.1
Summary: A plugin system for Django
Author: Simon Willison
License: Apache-2.0
Project-URL: Homepage, https://github.com/simonw/djp
Project-URL: Changelog, https://github.com/simonw/djp/releases
Project-URL: Issues, https://github.com/simonw/djp/issues
Project-URL: CI, https://github.com/simonw/djp/actions
Classifier: License :: OSI Approved :: Apache Software License
Requires-Python: >=3.8
License-File: LICENSE
Requires-Dist: django
Requires-Dist: pluggy
Provides-Extra: test
Requires-Dist: pytest ; extra == 'test'
Requires-Dist: pytest-django ; extra == 'test'
Requires-Dist: pytest-env ; extra == 'test'
Requires-Dist: pytest-asyncio ; extra == 'test'
Requires-Dist: httpx ; extra == 'test'
